{
    "rngdropjingle": {
        "category": "master",
        "sounds": [
            {
                "name": "partlysaneskies:rngdropjingle",
                "stream": true
            }
        ]
    },
    "airraidsiren": {
        "category": "master",
        "sounds": [
            {
                "name": "partlysaneskies:airraidsiren",
                "stream": true
            }
        ]
    },
    "bell": {
        "category": "master",
        "sounds": [
            {
                "name": "partlysaneskies:bell",
                "stream": false
            }
        ]
    },
    "flute_scale": {
        "category": "master",
        "sounds": [
            {
                "name": "partlysaneskies:flute_scale",
                "stream": false
            }
        ]
    },

    "tenor_piano": {
        "category": "record",
        "sounds": [
            {
                "name": "partlysaneskies:tenor_piano",
                "stream": false
            }
        ]
    },

    "alto_piano": {
        "category": "record",
        "sounds": [
            {
                "name" :"partlysaneskies:alto_piano",
                "stream" :false
            }   
            
        ]
    },

    "bass_piano": {
        "category": "record",
        "sounds": [
            {
                "name" : "partlysaneskies:bass_piano",
                "stream" : false
            }
        ]
    },

    "tenor_clarinet": {
        "category": "record",
        "sounds": [
            {
                "name": "partlysaneskies:tenor_clarinet",
                "stream": false
            }
        ]
    },

    "alto_clarinet": {
        "category": "record",
        "sounds": [
            {
                "name" :"partlysaneskies:alto_clarinet",
                "stream" :false
            }   
            
        ]
    },

    "bass_clarinet": {
        "category": "record",
        "sounds": [
            {
                "name" : "partlysaneskies:bass_clarinet",
                "stream" : false
            }
        ]
    },

    "tenor_electric_piano": {
        "category": "record",
        "sounds": [
            {
                "name": "partlysaneskies:tenor_electric_piano",
                "stream": false
            }
        ]
    },

    "alto_electric_piano": {
        "category": "record",
        "sounds": [
            {
                "name" :"partlysaneskies:alto_electric_piano",
                "stream" :false
            }   
            
        ]
    },

    "bass_electric_piano": {
        "category": "record",
        "sounds": [
            {
                "name" : "partlysaneskies:bass_electric_piano",
                "stream" : false
            }
        ]
    },

    "tenor_flute": {
        "category": "record",
        "sounds": [
            {
                "name": "partlysaneskies:tenor_flute",
                "stream": false
            }
        ]
    },

    "alto_flute": {
        "category": "record",
        "sounds": [
            {
                "name" :"partlysaneskies:alto_flute",
                "stream" :false
            }   
            
        ]
    },

    "bass_flute": {
        "category": "record",
        "sounds": [
            {
                "name" : "partlysaneskies:bass_flute",
                "stream" : false
            }
        ]
    },

    "tenor_organ": {
        "category": "record",
        "sounds": [
            {
                "name": "partlysaneskies:tenor_organ",
                "stream": false
            }
        ]
    },

    "alto_organ": {
        "category": "record",
        "sounds": [
            {
                "name" :"partlysaneskies:alto_organ",
                "stream" :false
            }   
            
        ]
    },

    "bass_organ": {
        "category": "record",
        "sounds": [
            {
                "name" : "partlysaneskies:bass_organ",
                "stream" : false
            }
        ]
    },

    "tenor_string_ensemble": {
        "category": "record",
        "sounds": [
            {
                "name": "partlysaneskies:tenor_string_ensemble",
                "stream": false
            }
        ]
    },

    "alto_string_ensemble": {
        "category": "record",
        "sounds": [
            {
                "name" :"partlysaneskies:alto_string_ensemble",
                "stream" :false
            }   
            
        ]
    },

    "bass_string_ensemble": {
        "category": "record",
        "sounds": [
            {
                "name" : "partlysaneskies:bass_string_ensemble",
                "stream" : false
            }
        ]
    },

    "tenor_trombone": {
        "category": "record",
        "sounds": [
            {
                "name": "partlysaneskies:tenor_trombone",
                "stream": false
            }
        ]
    },

    "alto_trombone": {
        "category": "record",
        "sounds": [
            {
                "name" :"partlysaneskies:alto_trombone",
                "stream" :false
            }   
            
        ]
    },

    "bass_trombone": {
        "category": "record",
        "sounds": [
            {
                "name" : "partlysaneskies:bass_trombone",
                "stream" : false
            }
        ]
    },

    "tenor_trumpet": {
        "category": "record",
        "sounds": [
            {
                "name": "partlysaneskies:tenor_trumpet",
                "stream": false
            }
        ]
    },

    "alto_trumpet": {
        "category": "record",
        "sounds": [
            {
                "name" :"partlysaneskies:alto_trumpet",
                "stream" :false
            }   
            
        ]
    },

    "bass_trumpet": {
        "category": "record",
        "sounds": [
            {
                "name" : "partlysaneskies:bass_trumpet",
                "stream" : false
            }
        ]
    },

    "tenor_violin": {
        "category": "record",
        "sounds": [
            {
                "name": "partlysaneskies:tenor_violin",
                "stream": false
            }
        ]
    },

    "alto_violin": {
        "category": "record",
        "sounds": [
            {
                "name" :"partlysaneskies:alto_violin",
                "stream" :false
            }   
            
        ]
    },

    "bass_violin": {
        "category": "record",
        "sounds": [
            {
                "name" : "partlysaneskies:bass_violin",
                "stream" : false
            }
        ]
    },

    "tenor_wind_ensemble": {
        "category": "record",
        "sounds": [
            {
                "name": "partlysaneskies:tenor_wind_ensemble",
                "stream": false
            }
        ]
    },

    "alto_wind_ensemble": {
        "category": "record",
        "sounds": [
            {
                "name" :"partlysaneskies:alto_wind_ensemble",
                "stream" :false
            }   
            
        ]
    },

    "bass_wind_ensemble": {
        "category": "record",
        "sounds": [
            {
                "name" : "partlysaneskies:bass_wind_ensemble",
                "stream" : false
            }
        ]
    },

    "tenor_live_clarinet": {
        "category": "record",
        "sounds": [
            {
                "name": "partlysaneskies:tenor_live_clarinet",
                "stream": false
            }
        ]
    },

    "alto_live_clarinet": {
        "category": "record",
        "sounds": [
            {
                "name" :"partlysaneskies:alto_live_clarinet",
                "stream" :false
            }   
            
        ]
    },

    "bass_live_clarinet": {
        "category": "record",
        "sounds": [
            {
                "name" : "partlysaneskies:bass_live_clarinet",
                "stream" : false
            }
        ]
    },

    "explosion": {
        "category": "record",
        "sounds": [
            {
                "name" : "partlysaneskies:explosion",
                "stream" : false
            }
        ]
    }

}